tima_timer/__init__.py
tima_timer/__main__.py
tima_timer/app.py
tima_timer/app_flet.py
tima_timer/py.typed
tima_timer/state.py
tima_timer-2.0.3.dist-info/WHEEL
tima_timer-2.0.3.dist-info/entry_points.txt
tima_timer-2.0.3.dist-info/METADATA
tima_timer-2.0.3.dist-info/RECORD
