Metadata-Version: 2.3
Name: tima-timer
Version: 2.0.3
Summary: A modern cross-platform productivity timer for managing multiple projects (Flet-based)
Keywords: timer,productivity,time-management,project-management
Author: Amir Rosenfeld
Author-email: Amir Rosenfeld <amir.rosenfeld@gmail.com>
License: MIT
Classifier: Development Status :: 4 - Beta
Classifier: Intended Audience :: End Users/Desktop
Classifier: License :: OSI Approved :: MIT License
Classifier: Topic :: Office/Business :: Scheduling
Classifier: Topic :: Utilities
Classifier: Operating System :: OS Independent
Classifier: Environment :: X11 Applications
Classifier: Environment :: Win32 (MS Windows)
Classifier: Environment :: MacOS X
Classifier: Programming Language :: Python :: 3
Classifier: Programming Language :: Python :: 3.8
Classifier: Programming Language :: Python :: 3.9
Classifier: Programming Language :: Python :: 3.10
Classifier: Programming Language :: Python :: 3.11
Classifier: Programming Language :: Python :: 3.12
Requires-Dist: flet[all]>=0.24.0
Requires-Python: >=3.8
Project-URL: Homepage, https://github.com/rosenfeldamir/tima
Project-URL: Issues, https://github.com/rosenfeldamir/tima/issues
Project-URL: Repository, https://github.com/rosenfeldamir/tima
